flexprice_sdk_test/__init__.py
flexprice_sdk_test/_version.py
flexprice_sdk_test/addons.py
flexprice_sdk_test/alert_logs.py
flexprice_sdk_test/auth.py
flexprice_sdk_test/basesdk.py
flexprice_sdk_test/connections.py
flexprice_sdk_test/costs.py
flexprice_sdk_test/coupons.py
flexprice_sdk_test/credit_notes.py
flexprice_sdk_test/creditgrants.py
flexprice_sdk_test/customers.py
flexprice_sdk_test/entitlements.py
flexprice_sdk_test/entity_integration_mappings.py
flexprice_sdk_test/environments.py
flexprice_sdk_test/events.py
flexprice_sdk_test/features.py
flexprice_sdk_test/groups.py
flexprice_sdk_test/httpclient.py
flexprice_sdk_test/integrations.py
flexprice_sdk_test/invoices.py
flexprice_sdk_test/payments.py
flexprice_sdk_test/plans.py
flexprice_sdk_test/price_units.py
flexprice_sdk_test/prices.py
flexprice_sdk_test/py.typed
flexprice_sdk_test/rbac.py
flexprice_sdk_test/scheduledtasks.py
flexprice_sdk_test/sdk.py
flexprice_sdk_test/sdkconfiguration.py
flexprice_sdk_test/secrets.py
flexprice_sdk_test/subscriptions.py
flexprice_sdk_test/tasks.py
flexprice_sdk_test/tax_associations.py
flexprice_sdk_test/tax_rates.py
flexprice_sdk_test/tenants.py
flexprice_sdk_test/users.py
flexprice_sdk_test/wallets.py
flexprice_sdk_test/webhooks.py
flexprice_sdk_test/_hooks/__init__.py
flexprice_sdk_test/_hooks/registration.py
flexprice_sdk_test/_hooks/sdkhooks.py
flexprice_sdk_test/_hooks/types.py
flexprice_sdk_test/models/__init__.py
flexprice_sdk_test/models/components/__init__.py
flexprice_sdk_test/models/components/costsheet_filter.py
flexprice_sdk_test/models/components/creditnote_creditnotelineitem.py
flexprice_sdk_test/models/components/dto_activatedraftsubscriptionrequest.py
flexprice_sdk_test/models/components/dto_addaddonrequest.py
flexprice_sdk_test/models/components/dto_addaddontosubscriptionrequest.py
flexprice_sdk_test/models/components/dto_addonassociationresponse.py
flexprice_sdk_test/models/components/dto_addonresponse.py
flexprice_sdk_test-2.0.20260104134957.dist-info/METADATA
flexprice_sdk_test-2.0.20260104134957.dist-info/WHEEL
flexprice_sdk_test-2.0.20260104134957.dist-info/top_level.txt
flexprice_sdk_test-2.0.20260104134957.dist-info/RECORD
