Metadata-Version: 2.4
Name: flexprice-sdk-test
Version: 2.0.20260104134957
Summary: Python SDK for FlexPrice API
Home-page: https://github.com/flexprice/python-sdk
Author: Speakeasy
Author-email: tech@flexprice.io
Project-URL: Repository, https://github.com/flexprice/flexprice
Project-URL: Homepage, https://github.com/flexprice/flexprice
Requires-Python: >= 3.8
Requires-Dist: httpcore>=1.0.9
Requires-Dist: httpx>=0.28.1
Requires-Dist: pydantic>=2.11.2
Dynamic: author-email
Dynamic: home-page
Dynamic: requires-python
